setup.py
wsgi_jsonrpc/__init__.py
wsgi_jsonrpc/json_tools.py
wsgi_jsonrpc/test_jsonrpc.py
wsgi_jsonrpc.egg-info/PKG-INFO
wsgi_jsonrpc.egg-info/SOURCES.txt
wsgi_jsonrpc.egg-info/dependency_links.txt
wsgi_jsonrpc.egg-info/setup.py
wsgi_jsonrpc.egg-info/top_level.txt
wsgi_jsonrpc.egg-info/wsgi_jsonrpc/__init__.py
wsgi_jsonrpc.egg-info/wsgi_jsonrpc/__init__.pyc
wsgi_jsonrpc.egg-info/wsgi_jsonrpc/json_tools.py
wsgi_jsonrpc.egg-info/wsgi_jsonrpc/json_tools.pyc
wsgi_jsonrpc.egg-info/wsgi_jsonrpc/test_jsonrpc.py
wsgi_jsonrpc.egg-info/wsgi_jsonrpc/test_jsonrpc.pyc