Metadata-Version: 1.0
Name: wsgi-jsonrpc
Version: 0.2.8
Summary: WSGI jsonrpc application
Home-page: http://code.google.com/p/wsgi-jsonrpc/
Author: OSAF, Mikeal Rogers
Author-email: mikeal.rogers@gmail.com
License: http://www.apache.org/licenses/LICENSE-2.0
Platform: Any
Classifier: Development Status :: 4 - Beta
Classifier: Environment :: Console
Classifier: Intended Audience :: Developers
Classifier: License :: OSI Approved :: Apache Software License
Classifier: Operating System :: OS Independent
Classifier: Topic :: Software Development :: Libraries :: Python Modules
